xillar/__init__.py
xillar-0.0.1.dist-info/METADATA
xillar-0.0.1.dist-info/WHEEL
xillar-0.0.1.dist-info/top_level.txt
xillar-0.0.1.dist-info/RECORD
