Metadata-Version: 2.1
Name: xillar
Version: 0.0.1
Summary: xillar
Home-page: UNKNOWN
Author: Amit Garu
Author-email: amitgaru2@gmail.com
License: MIT
Keywords: xillar
Platform: UNKNOWN
Classifier: Programming Language :: Python :: 3
Classifier: License :: OSI Approved :: MIT License
Classifier: Operating System :: OS Independent
Requires-Python: >=3.5
